{
  "stories": [
    {
      "id": "src-lib-components-shipedit-story-svelte",
      "title": "ShipEdit",
      "group": null,
      "layout": {
        "type": "single",
        "iframe": true
      },
      "icon": null,
      "iconColor": null,
      "docsOnly": false,
      "variants": [
        {
          "id": "_default",
          "title": "default"
        }
      ],
      "relativePath": "src/lib/components/ShipEdit.story.svelte",
      "supportPluginId": "svelte3",
      "treePath": [
        "ShipEdit"
      ],
      "virtual": false,
      "markdownFile": null
    },
    {
      "id": "src-lib-components-shipitem-story-svelte",
      "title": "ShipItem",
      "group": null,
      "layout": {
        "type": "single",
        "iframe": true
      },
      "icon": null,
      "iconColor": null,
      "docsOnly": false,
      "variants": [
        {
          "id": "_default",
          "title": "default"
        }
      ],
      "relativePath": "src/lib/components/ShipItem.story.svelte",
      "supportPluginId": "svelte3",
      "treePath": [
        "ShipItem"
      ],
      "virtual": false,
      "markdownFile": null
    },
    {
      "id": "src-lib-components-costmass-index-story-svelte",
      "title": "CostMass",
      "group": null,
      "layout": {
        "type": "single",
        "iframe": true
      },
      "icon": null,
      "iconColor": null,
      "docsOnly": false,
      "variants": [
        {
          "id": "_default",
          "title": "default"
        }
      ],
      "relativePath": "src/lib/components/CostMass/index.story.svelte",
      "supportPluginId": "svelte3",
      "treePath": [
        "CostMass"
      ],
      "virtual": false,
      "markdownFile": null
    },
    {
      "id": "src-lib-components-shipedit-carrier-story-svelte",
      "title": "Carrier",
      "group": null,
      "layout": {
        "type": "single",
        "iframe": true
      },
      "icon": null,
      "iconColor": null,
      "docsOnly": false,
      "variants": [
        {
          "id": "_default",
          "title": "default"
        }
      ],
      "relativePath": "src/lib/components/ShipEdit/Carrier.story.svelte",
      "supportPluginId": "svelte3",
      "treePath": [
        "ShipEdit",
        "Carrier"
      ],
      "virtual": false,
      "markdownFile": null
    },
    {
      "id": "src-lib-components-shipedit-identification-story-svelte",
      "title": "Identification",
      "group": null,
      "layout": {
        "type": "single",
        "iframe": true
      },
      "icon": null,
      "iconColor": null,
      "docsOnly": false,
      "variants": [
        {
          "id": "_default",
          "title": "default"
        }
      ],
      "relativePath": "src/lib/components/ShipEdit/Identification.story.svelte",
      "supportPluginId": "svelte3",
      "treePath": [
        "ShipEdit",
        "Identification"
      ],
      "virtual": false,
      "markdownFile": null
    },
    {
      "id": "src-lib-components-shipedit-propulsion-engine-story-svelte",
      "title": "Engine",
      "group": null,
      "layout": {
        "type": "single",
        "iframe": true
      },
      "icon": null,
      "iconColor": null,
      "docsOnly": false,
      "variants": [
        {
          "id": "_default",
          "title": "default"
        }
      ],
      "relativePath": "src/lib/components/ShipEdit/Propulsion/Engine.story.svelte",
      "supportPluginId": "svelte3",
      "treePath": [
        "ShipEdit",
        "Propulsion",
        "Engine"
      ],
      "virtual": false,
      "markdownFile": null
    },
    {
      "id": "src-routes-export-print-printship-index-story-svelte",
      "title": "PrintShip",
      "group": null,
      "layout": {
        "type": "single",
        "iframe": true
      },
      "icon": null,
      "iconColor": null,
      "docsOnly": false,
      "variants": [
        {
          "id": "_default",
          "title": "default"
        }
      ],
      "relativePath": "src/routes/export/print/PrintShip/index.story.svelte",
      "supportPluginId": "svelte3",
      "treePath": [
        "Export",
        "PrintShip"
      ],
      "virtual": false,
      "markdownFile": null
    },
    {
      "id": "src-routes-export-print-printship-armor-index-story-svelte",
      "title": "Armor",
      "group": null,
      "layout": {
        "type": "single",
        "iframe": true
      },
      "icon": null,
      "iconColor": null,
      "docsOnly": false,
      "variants": [
        {
          "id": "src-routes-export-print-printship-armor-index-story-svelte-0",
          "title": "untitled",
          "icon": null,
          "iconColor": null
        }
      ],
      "relativePath": "src/routes/export/print/PrintShip/Armor/index.story.svelte",
      "supportPluginId": "svelte3",
      "treePath": [
        "Export",
        "PrintShip",
        "Armor"
      ],
      "virtual": false,
      "markdownFile": null
    },
    {
      "id": "src-routes-export-print-printship-hull-index-story-svelte",
      "title": "Hull",
      "group": null,
      "layout": {
        "type": "single",
        "iframe": true
      },
      "icon": null,
      "iconColor": null,
      "docsOnly": false,
      "variants": [
        {
          "id": "src-routes-export-print-printship-hull-index-story-svelte-0",
          "title": "untitled",
          "icon": null,
          "iconColor": null
        }
      ],
      "relativePath": "src/routes/export/print/PrintShip/Hull/index.story.svelte",
      "supportPluginId": "svelte3",
      "treePath": [
        "Export",
        "PrintShip",
        "Hull"
      ],
      "virtual": false,
      "markdownFile": null
    },
    {
      "id": "src-routes-export-print-printship-screens-index-story-svelte",
      "title": "Screens",
      "group": null,
      "layout": {
        "type": "single",
        "iframe": true
      },
      "icon": null,
      "iconColor": null,
      "docsOnly": false,
      "variants": [
        {
          "id": "src-routes-export-print-printship-screens-index-story-svelte-0",
          "title": "untitled",
          "icon": null,
          "iconColor": null
        }
      ],
      "relativePath": "src/routes/export/print/PrintShip/Screens/index.story.svelte",
      "supportPluginId": "svelte3",
      "treePath": [
        "Export",
        "PrintShip",
        "Screens"
      ],
      "virtual": false,
      "markdownFile": null
    },
    {
      "id": "src-routes-export-print-printship-weapons-index-story-svelte",
      "title": "Weapons",
      "group": null,
      "layout": {
        "type": "single",
        "iframe": true
      },
      "icon": null,
      "iconColor": null,
      "docsOnly": false,
      "variants": [
        {
          "id": "_default",
          "title": "default"
        }
      ],
      "relativePath": "src/routes/export/print/PrintShip/Weapons/index.story.svelte",
      "supportPluginId": "svelte3",
      "treePath": [
        "Export",
        "PrintShip",
        "Weapons"
      ],
      "virtual": false,
      "markdownFile": null
    }
  ],
  "markdownFiles": []
}